nerdman.py
nerdman-0.1.1.dist-info/licenses/LICENSE
nerdman-0.1.1.dist-info/METADATA
nerdman-0.1.1.dist-info/WHEEL
nerdman-0.1.1.dist-info/entry_points.txt
nerdman-0.1.1.dist-info/top_level.txt
nerdman-0.1.1.dist-info/RECORD
