Metadata-Version: 2.4
Name: nerdman
Version: 0.1.1
Summary: A powerful Python library and CLI tool for working with Nerd Fonts icons
Home-page: https://github.com/mralfiem591/nerdman
Author: Alfie McCabe
Author-email: Alfie McCabe <iamamccabe@gmail.com>
Maintainer-email: Alfie McCabe <iamamccabe@gmail.com>
License: MIT
Project-URL: Homepage, https://github.com/mralfiem591/nerdman
Project-URL: Documentation, https://github.com/mralfiem591/nerdman#readme
Project-URL: Repository, https://github.com/mralfiem591/nerdman.git
Project-URL: Bug Reports, https://github.com/mralfiem591/nerdman/issues
Project-URL: Changelog, https://github.com/mralfiem591/nerdman/blob/main/CHANGELOG.md
Keywords: nerd-fonts,icons,fonts,cli,terminal,unicode,symbols,glyphs,developer-tools,font-icons
Platform: any
Classifier: Development Status :: 4 - Beta
Classifier: Intended Audience :: Developers
Classifier: Topic :: Software Development :: Libraries :: Python Modules
Classifier: License :: OSI Approved :: MIT License
Classifier: Programming Language :: Python :: 3
Classifier: Programming Language :: Python :: 3.7
Classifier: Programming Language :: Python :: 3.8
Classifier: Programming Language :: Python :: 3.9
Classifier: Programming Language :: Python :: 3.10
Classifier: Programming Language :: Python :: 3.11
Classifier: Programming Language :: Python :: 3.12
Classifier: Operating System :: OS Independent
Classifier: Environment :: Console
Classifier: Natural Language :: English
Requires-Python: >=3.7
License-File: LICENSE
Provides-Extra: dev
Requires-Dist: pytest>=6.0; extra == "dev"
Requires-Dist: pytest-cov; extra == "dev"
Requires-Dist: black; extra == "dev"
Requires-Dist: flake8; extra == "dev"
Requires-Dist: mypy; extra == "dev"
Requires-Dist: twine; extra == "dev"
Requires-Dist: wheel; extra == "dev"
Provides-Extra: test
Requires-Dist: pytest>=6.0; extra == "test"
Requires-Dist: pytest-cov; extra == "test"
Dynamic: author
Dynamic: home-page
Dynamic: license-file
Dynamic: platform
Dynamic: requires-python
